tests/__init__.py
tests/test_adapter.py
tingg/__init__.py
tingg/adapters.py
tingg/exceptions.py
utils/Encryption.py
utils/__init__.py
qatingg-2.0.5.dist-info/LICENSE
qatingg-2.0.5.dist-info/METADATA
qatingg-2.0.5.dist-info/WHEEL
qatingg-2.0.5.dist-info/top_level.txt
qatingg-2.0.5.dist-info/RECORD
