Metadata-Version: 2.1
Name: qatingg
Version: 2.0.5
Summary: Cellulant QA adapter
Home-page: https://tingg.africa
Author: SKingori
Author-email: samson.mwangi@cllulant.com
License: GPLv3+
Platform: UNKNOWN
Classifier: Environment :: Web Environment
Classifier: Intended Audience :: Developers
Classifier: Operating System :: OS Independent
Classifier: Programming Language :: Python
Classifier: Topic :: Internet :: WWW/HTTP
Classifier: Topic :: Internet :: WWW/HTTP :: Dynamic Content
Requires-Python: >=3.7
Requires-Dist: pycryptodome
Requires-Dist: requests
